{
	"configurations" : 
	[
		{
			"directories" : 
			[
				{
					"build" : ".",
					"minimumCMakeVersion" : 
					{
						"string" : "3.5"
					},
					"projectIndex" : 0,
					"source" : ".",
					"targetIndexes" : 
					[
						0
					]
				}
			],
			"name" : "Release",
			"projects" : 
			[
				{
					"directoryIndexes" : 
					[
						0
					],
					"name" : "CGAssignment1",
					"targetIndexes" : 
					[
						0
					]
				}
			],
			"targets" : 
			[
				{
					"directoryIndex" : 0,
					"id" : "CGAssignment1::@6890427a1f51a3e7e1df",
					"jsonFile" : "target-CGAssignment1-Release-ad616c57f0612851f703.json",
					"name" : "CGAssignment1",
					"projectIndex" : 0
				}
			]
		}
	],
	"kind" : "codemodel",
	"paths" : 
	{
		"build" : "C:/Users/Administrator/Desktop/计图作业/Assignment1_3D_Transformation/CGAssignment1/out/build/x64-Debug",
		"source" : "C:/Users/Administrator/Desktop/计图作业/Assignment1_3D_Transformation/CGAssignment1"
	},
	"version" : 
	{
		"major" : 2,
		"minor" : 2
	}
}
